simplified_keras/__init__.py
simplified_keras/callbacks.py
simplified_keras/default_callbacks.py
simplified_keras/generators.py
simplified_keras/tools.py
simplified_keras/metrics/__init__.py
simplified_keras/plots/__init__.py
simplified_keras/plots/history_plots.py
simplified_keras/transformations/__init__.py
simplified_keras/transformations/layers.py
simplified_keras-0.0.22.dist-info/LICENSE
simplified_keras-0.0.22.dist-info/METADATA
simplified_keras-0.0.22.dist-info/WHEEL
simplified_keras-0.0.22.dist-info/top_level.txt
simplified_keras-0.0.22.dist-info/RECORD
