Metadata-Version: 2.1
Name: simplified-keras
Version: 0.0.22
Summary: Common used code in Keras
Home-page: https://github.com/albertlis/simplified-keras
Author: Albert Lis
Author-email: albert.lis.1996@gmail.com
License: UNKNOWN
Keywords: keras,utils
Platform: UNKNOWN
Classifier: Programming Language :: Python :: 3
Classifier: Programming Language :: Python :: 3.8
Classifier: License :: OSI Approved :: MIT License
Classifier: Operating System :: OS Independent
Classifier: Intended Audience :: Developers
Classifier: Intended Audience :: Education
Classifier: Intended Audience :: Science/Research
Classifier: Natural Language :: English
Classifier: Topic :: Scientific/Engineering
Classifier: Topic :: Scientific/Engineering :: Artificial Intelligence
Classifier: Topic :: Scientific/Engineering :: Image Processing
Classifier: Topic :: Scientific/Engineering :: Image Recognition
Classifier: Topic :: Scientific/Engineering :: Mathematics
Classifier: Topic :: Scientific/Engineering :: Visualization
Requires-Dist: matplotlib (>=3.0)
Requires-Dist: numpy (>=1.0)
Requires-Dist: tensorflow-gpu (>=2.4.1)
Requires-Dist: seaborn (>=0.10)
Requires-Dist: pandas (>=1.0)
Requires-Dist: opencv-python (>=4.0.0)
